auth0_lambda_server/app.py
auth0_lambda_server-0.1.1.dist-info/METADATA
auth0_lambda_server-0.1.1.dist-info/WHEEL
auth0_lambda_server-0.1.1.dist-info/licenses/LICENSE
auth0_lambda_server-0.1.1.dist-info/RECORD
